CHANGELOG.rst
CONTRIBUTORS.rst
LICENSE.txt
MANIFEST.in
README.rst
requirements.txt
run_tests.sh
setup.py
bin/wa_kat_build_conspects.py
bin/wa_kat_build_keyword_index.py
bin/wa_kat_server.py
bin/wa_kat_structured_logger.py
docs/Makefile
docs/__init__.py
docs/admin_manual.rst
docs/conf.py
docs/index.rst
docs/manual.rst
docs/api/data_model.rst
docs/api/logger.rst
docs/api/settings.rst
docs/api/wa_kat.rst
docs/api/analyzers/analyzers.rst
docs/api/analyzers/annotation_detector.rst
docs/api/analyzers/author_detector.rst
docs/api/analyzers/creation_date_detector.rst
docs/api/analyzers/keyword_detector.rst
docs/api/analyzers/language_detector.rst
docs/api/analyzers/place_detector.rst
docs/api/analyzers/shared.rst
docs/api/analyzers/source_string.rst
docs/api/analyzers/title_detector.rst
docs/api/connectors/aleph.rst
docs/api/connectors/connectors.rst
docs/api/connectors/seeder.rst
docs/api/convertors/convertors.rst
docs/api/convertors/iso_codes.rst
docs/api/convertors/mrc.rst
docs/api/convertors/to_dc.rst
docs/api/db/db.rst
docs/api/db/downloader.rst
docs/api/db/request_info.rst
docs/api/db/worker.rst
docs/api/rest_api/aleph_api.rst
docs/api/rest_api/analyzers_api.rst
docs/api/rest_api/bottle_index.rst
docs/api/rest_api/db.rst
docs/api/rest_api/keywords.rst
docs/api/rest_api/rest_api.rst
docs/api/rest_api/shared.rst
docs/api/rest_api/to_output.rst
docs/api/rest_api/virtual_fs.rst
src/wa_kat/__init__.py
src/wa_kat/data_model.py
src/wa_kat/logger.py
src/wa_kat/settings.py
src/wa_kat.egg-info/PKG-INFO
src/wa_kat.egg-info/SOURCES.txt
src/wa_kat.egg-info/dependency_links.txt
src/wa_kat.egg-info/not-zip-safe
src/wa_kat.egg-info/requires.txt
src/wa_kat.egg-info/top_level.txt
src/wa_kat/analyzers/__init__.py
src/wa_kat/analyzers/annotation_detector.py
src/wa_kat/analyzers/author_detector.py
src/wa_kat/analyzers/creation_date_detector.py
src/wa_kat/analyzers/keyword_detector.py
src/wa_kat/analyzers/language_detector.py
src/wa_kat/analyzers/place_detector.py
src/wa_kat/analyzers/shared.py
src/wa_kat/analyzers/source_string.py
src/wa_kat/analyzers/title_detector.py
src/wa_kat/connectors/__init__.py
src/wa_kat/connectors/aleph.py
src/wa_kat/connectors/seeder.py
