Metadata-Version: 2.1
Name: wa-kat
Version: 1.1.14
Summary: Web page analyzator for czech webarchive.
Home-page: https://github.com/WebArchivCZ/WA-KAT
Author: Bystroushaak
Author-email: bystrousak@kitakitsune.org
License: MIT
Platform: UNKNOWN
Classifier: Development Status :: 3 - Alpha
Classifier: Programming Language :: Python
Classifier: Programming Language :: Python :: 2.7
Classifier: Intended Audience :: Developers
Classifier: License :: OSI Approved :: MIT License
Provides-Extra: test
Provides-Extra: docs
